imaxt_registration/__init__.py
imaxt_registration/axio2stpt.py
imaxt_registration/contourlib.py
imaxt_registration/plotting.py
imaxt_registration/registration.py
imaxt_registration/settings.py
imaxt_registration/terminal.py
imaxt_registration_tools-0.2.1.dist-info/METADATA
imaxt_registration_tools-0.2.1.dist-info/WHEEL
imaxt_registration_tools-0.2.1.dist-info/entry_points.txt
imaxt_registration_tools-0.2.1.dist-info/top_level.txt
imaxt_registration_tools-0.2.1.dist-info/RECORD
