Metadata-Version: 2.1
Name: imaxt-registration-tools
Version: 0.2.1
Summary: Image registration tools for IMAXT
Home-page: https://gitlab.developers.cam.ac.uk/astronomy/camcead/imaxt/imaxt-registration-tools
Author: attr: imaxt_registration.__author__
Author-email: "E.GonzalezSolares@ast.cam.ac.uk"
Project-URL: Bug Tracker, https://gitlab.developers.cam.ac.uk/astronomy/camcead/imaxt/imaxt-registration-tools/-/issues
Classifier: Development Status :: 4 - Beta
Classifier: Programming Language :: Python
Classifier: Programming Language :: Python :: 3
Classifier: Programming Language :: Python :: 3.9
Classifier: Programming Language :: Python :: 3.10
Classifier: License :: OSI Approved :: MIT License
Classifier: Operating System :: OS Independent
Requires-Python: >=3.7
Requires-Dist: xarray
Requires-Dist: scipy
Requires-Dist: numpy
Requires-Dist: opencv-python-headless
Requires-Dist: scikit-image
Requires-Dist: pandas
Requires-Dist: dask
Requires-Dist: zarr
Requires-Dist: pyarrow
Requires-Dist: SimpleITK
Requires-Dist: matplotlib
Requires-Dist: colored
Requires-Dist: msgpack
Requires-Dist: msgpack-numpy
